lib_hero/__init__.py
lib_hero/main.py
lib_hero/controller/__initi__.py
lib_hero/controller/generic.py
lib_hero/controller/hero.py
lib_hero/controller/team.py
lib_hero/model/__init__.py
lib_hero/model/dto.py
lib_hero/model/models.py
lib_hero/repository/__init__.py
lib_hero/repository/base.py
lib_hero/service/__init__.py
lib_hero/service/base.py
lib_hero/util/__init__.py
lib_hero/util/database.py
lib_hero_raf-0.1.4.dist-info/METADATA
lib_hero_raf-0.1.4.dist-info/WHEEL
lib_hero_raf-0.1.4.dist-info/top_level.txt
lib_hero_raf-0.1.4.dist-info/RECORD
