Metadata-Version: 2.4
Name: lib-hero-raf
Version: 0.1.4
Summary: Biblioteca MVC de Hero usada na atividade da disciplina.
Author-email: Rafael <rafaeldeps15@gmail.com>
Requires-Python: >=3.9
Requires-Dist: fastapi
Requires-Dist: sqlmodel
Requires-Dist: pydantic
